Metadata-Version: 1.0
Name: okt-distributions
Version: 0.1
Summary: Gaussian and Binomial distributions
Home-page: UNKNOWN
Author: Oktay Ergun
Author-email: oergun45@gmail.com
License: UNKNOWN
Platform: UNKNOWN
